osmem/__init__.py
osmem/__main__.py
osmem/cli.py
osmem/memory.py
osmem/process.py
osmem/windows.py
osmem-0.3.2.dist-info/METADATA
osmem-0.3.2.dist-info/WHEEL
osmem-0.3.2.dist-info/entry_points.txt
osmem-0.3.2.dist-info/licenses/LICENSE
osmem-0.3.2.dist-info/RECORD
