Metadata-Version: 2.4
Name: osmem
Version: 0.3.2
Summary: Shows memory usage information for process trees
License: GPLv2
License-File: LICENSE
Keywords: memory,ps,process,top,tree
Author: jojje
Author-email: tinjon+pypi@gmail.com
Requires-Python: >=3.9,<4
Classifier: Development Status :: 4 - Beta
Classifier: License :: OSI Approved :: GNU General Public License v2 (GPLv2)
Classifier: License :: Other/Proprietary License
Classifier: Operating System :: MacOS
Classifier: Operating System :: Microsoft :: Windows
Classifier: Operating System :: POSIX :: Linux
Classifier: Programming Language :: Python :: 3
Classifier: Programming Language :: Python :: 3.9
Classifier: Programming Language :: Python :: 3.10
Classifier: Programming Language :: Python :: 3.11
Classifier: Programming Language :: Python :: 3.12
Classifier: Programming Language :: Python :: 3.13
Classifier: Programming Language :: Python :: 3.14
Requires-Dist: psutil (>=5.7)
